setup.py
scripts/steroids
steroids/__init__.py
steroids/installation.py
steroids.egg-info/PKG-INFO
steroids.egg-info/SOURCES.txt
steroids.egg-info/dependency_links.txt
steroids.egg-info/top_level.txt
steroids/modules/__init__.py
steroids/modules/angularjs.py
steroids/modules/apscheduler.py
steroids/modules/bootstrap.py
steroids/modules/flask.py
steroids/modules/flasktornado.py
steroids/modules/gae.py
steroids/modules/gunicorn.py
steroids/modules/honcho.py
steroids/modules/jquery.py
steroids/modules/mongodb.py
steroids/modules/rethinkdb.py
steroids/modules/socketio.py
steroids/modules/topcoat.py