Metadata-Version: 1.0
Name: steroids
Version: 0.12.3
Summary: Steroids is a set of tools to help python developers to build cool stuff reducing efforts and time.
Home-page: https://github.com/koalalorenzo/Steroids
Author: Lorenzo Setale ( http://who.is.lorenzo.setale.me/? )
Author-email: koalalorenzo@gmail.com
License: UNKNOWN
Platform: UNKNOWN
